multiwhacamole/README.MD
multiwhacamole/__init__.py
multiwhacamole/requirements.txt
multiwhacamole/thirdparty.json
multiwhacamole-0.10.dist-info/LICENSE.rst
multiwhacamole-0.10.dist-info/METADATA
multiwhacamole-0.10.dist-info/WHEEL
multiwhacamole-0.10.dist-info/top_level.txt
multiwhacamole-0.10.dist-info/RECORD
