Metadata-Version: 2.1
Name: multiwhacamole
Version: 0.10
Summary: Detects differences between a Single Image and a List of Images (multiprocessing)
Home-page: https://github.com/hansalemaos/multiwhacamole
Author: Johannes Fischer
Author-email: aulasparticularesdealemaosp@gmail.com
License: MIT
Keywords: multiprocessing,differences,image
Classifier: Development Status :: 4 - Beta
Classifier: Programming Language :: Python :: 3 :: Only
Classifier: Programming Language :: Python :: 3.10
Classifier: Topic :: Software Development :: Libraries :: Python Modules
Classifier: Topic :: Utilities
License-File: LICENSE.rst
Requires-Dist: a-cv2-easy-resize
Requires-Dist: a-cv-imwrite-imread-plus
Requires-Dist: a-pandas-ex-apply-ignore-exceptions
Requires-Dist: multicv2resize
Requires-Dist: multiprocca
Requires-Dist: numexpr
Requires-Dist: numpy
Requires-Dist: opencv-python
Requires-Dist: pandas
